arp_standard_model/__init__.py
arp_standard_model/_generated.py
arp_standard_model/_requests.py
arp_standard_model/py.typed
arp_standard_model-0.3.7.dist-info/licenses/LICENSE
arp_standard_model-0.3.7.dist-info/METADATA
arp_standard_model-0.3.7.dist-info/WHEEL
arp_standard_model-0.3.7.dist-info/top_level.txt
arp_standard_model-0.3.7.dist-info/RECORD
