Metadata-Version: 2.4
Name: arp-standard-model
Version: 0.3.7
Summary: Pydantic models for the ARP Standard (v1).
Author: Agent Runtime Protocol
License-Expression: MIT
Project-URL: Repository, https://github.com/AgentRuntimeProtocol/ARP_Standard
Project-URL: Issues, https://github.com/AgentRuntimeProtocol/ARP_Standard/issues
Requires-Python: >=3.11
License-File: LICENSE
Requires-Dist: pydantic>=2.6.0
Provides-Extra: dev
Requires-Dist: pyright>=1.1.0; extra == "dev"
Dynamic: license-file
